{
  "mapping": {
    "dependsOn": [
      "000-bootstrap"
    ],
    "implementingPaths": [
      {
        "path": "README.md",
        "source": "spec-edge"
      }
    ],
    "resolvedUnits": [
      {
        "locations": [
          {
            "file": "README.md"
          }
        ],
        "ownership": true,
        "sourceField": "establishes",
        "unit": {
          "kind": "file",
          "path": "README.md"
        }
      }
    ],
    "specId": "001-stagecraft-thesis",
    "specStatus": "approved"
  },
  "schemaVersion": "1.1.0",
  "shardHash": "afc0cc485f5329d57455eee37f00077d6c7fc6e7a73e3f65b5783a3bc6a324e1"
}
