{
  "mapping": {
    "dependsOn": [
      "002-app-shell",
      "003-postgres-adoption"
    ],
    "implementingPaths": [
      {
        "path": "backend/tenants/",
        "source": "spec-edge"
      }
    ],
    "resolvedUnits": [
      {
        "locations": [
          {
            "file": "backend/tenants/"
          }
        ],
        "ownership": true,
        "sourceField": "establishes",
        "unit": {
          "kind": "directory",
          "path": "backend/tenants/"
        }
      }
    ],
    "specId": "004-tenants-github-app",
    "specStatus": "approved"
  },
  "schemaVersion": "1.1.0",
  "shardHash": "2572be336088a2dcab42a1d15587b6c9a10a4cad8980d0f0c4d9b702db51d050"
}
