{
  "mapping": {
    "dependsOn": [
      "001-statecraft-thesis"
    ],
    "implementingPaths": [
      {
        "path": "infra/",
        "source": "spec-edge"
      }
    ],
    "resolvedUnits": [
      {
        "locations": [
          {
            "file": "infra/"
          }
        ],
        "ownership": true,
        "sourceField": "establishes",
        "unit": {
          "kind": "directory",
          "path": "infra/"
        }
      }
    ],
    "specId": "010-statecraft-cluster",
    "specStatus": "approved"
  },
  "schemaVersion": "1.1.0",
  "shardHash": "1a0b204380940d095cb3534d0a6f03b224f37383c2429ba71b53a0697d70eadf"
}
